qiyas/__init__.py
qiyas/construction/__init__.py
qiyas/construction/graph.py
qiyas/construction/reader.py
qiyas/conversion/__init__.py
qiyas/conversion/convertor.py
qiyas/conversion/reader.py
qiyas/unit_graphs/length.qs
qiyas/unit_graphs/mass.qs
qiyas/unit_graphs/volume.qs
qiyas/unit_tables/length_conversions.csv
qiyas/unit_tables/length_names.csv
qiyas/unit_tables/mass_conversions.csv
qiyas/unit_tables/mass_names.csv
qiyas/unit_tables/volume_conversions.csv
qiyas/unit_tables/volume_names.csv
qiyas-0.2.3.dist-info/LICENSE
qiyas-0.2.3.dist-info/METADATA
qiyas-0.2.3.dist-info/WHEEL
qiyas-0.2.3.dist-info/top_level.txt
qiyas-0.2.3.dist-info/RECORD
