Metadata-Version: 2.1
Name: qiyas
Version: 0.2.3
Summary: qiyas - A lightweight non-opinionated customizable unit conversion Python library
Home-page: https://github.com/MosGeo/qiyas
Author: Mustafa A. Al Ibrahim
Author-email: mustafa.geoscientist@outlook.com
License: UNKNOWN
Platform: UNKNOWN
Classifier: License :: OSI Approved :: MIT License
Classifier: Programming Language :: Python :: 3
Requires-Python: >=3.7
License-File: LICENSE
Requires-Dist: networkx
Requires-Dist: varname
Provides-Extra: dev
Requires-Dist: build ; extra == 'dev'
Requires-Dist: pylint ; extra == 'dev'
Requires-Dist: pytest ; extra == 'dev'
Requires-Dist: coverage ; extra == 'dev'
Requires-Dist: mypy ; extra == 'dev'
Requires-Dist: black ; extra == 'dev'
